MANIFEST.in
README.rst
setup.py
Products/__init__.py
Products.SimpleGroupsManagement.egg-info/PKG-INFO
Products.SimpleGroupsManagement.egg-info/SOURCES.txt
Products.SimpleGroupsManagement.egg-info/dependency_links.txt
Products.SimpleGroupsManagement.egg-info/entry_points.txt
Products.SimpleGroupsManagement.egg-info/namespace_packages.txt
Products.SimpleGroupsManagement.egg-info/not-zip-safe
Products.SimpleGroupsManagement.egg-info/requires.txt
Products.SimpleGroupsManagement.egg-info/top_level.txt
Products/SimpleGroupsManagement/__init__.py
Products/SimpleGroupsManagement/configure.zcml
Products/SimpleGroupsManagement/group_event.py
Products/SimpleGroupsManagement/interfaces.py
Products/SimpleGroupsManagement/Extensions/install.py
Products/SimpleGroupsManagement/browser/__init__.py
Products/SimpleGroupsManagement/browser/configure.zcml
Products/SimpleGroupsManagement/browser/controlpanel.py
Products/SimpleGroupsManagement/browser/group_management_permission.py
Products/SimpleGroupsManagement/browser/groupevent.png
Products/SimpleGroupsManagement/browser/manage_group_template.pt
Products/SimpleGroupsManagement/browser/simple_groups_management.pt
Products/SimpleGroupsManagement/browser/simple_groups_management.py
Products/SimpleGroupsManagement/locales/Products.SimpleGroupsManagement-manual.pot
Products/SimpleGroupsManagement/locales/Products.SimpleGroupsManagement.pot
Products/SimpleGroupsManagement/locales/plone.pot
Products/SimpleGroupsManagement/locales/rebuildAll.sh
Products/SimpleGroupsManagement/locales/ca/LC_MESSAGES/Products.SimpleGroupsManagement.mo
Products/SimpleGroupsManagement/locales/ca/LC_MESSAGES/Products.SimpleGroupsManagement.po
Products/SimpleGroupsManagement/locales/ca/LC_MESSAGES/plone.mo
Products/SimpleGroupsManagement/locales/ca/LC_MESSAGES/plone.po
Products/SimpleGroupsManagement/locales/es/LC_MESSAGES/Products.SimpleGroupsManagement.mo
Products/SimpleGroupsManagement/locales/es/LC_MESSAGES/Products.SimpleGroupsManagement.po
Products/SimpleGroupsManagement/locales/es/LC_MESSAGES/plone.mo
Products/SimpleGroupsManagement/locales/es/LC_MESSAGES/plone.po
Products/SimpleGroupsManagement/locales/fr/LC_MESSAGES/Products.SimpleGroupsManagement.mo
Products/SimpleGroupsManagement/locales/fr/LC_MESSAGES/Products.SimpleGroupsManagement.po
Products/SimpleGroupsManagement/locales/fr/LC_MESSAGES/plone.mo
Products/SimpleGroupsManagement/locales/fr/LC_MESSAGES/plone.po
