Metadata-Version: 1.1
Name: Products.SimpleGroupsManagement
Version: 0.5.0
Summary: A Plone utility that let non-Manager users able to manage some (specific) groups
Home-page: https://github.com/keul/Products.SimpleGroupsManagement
Author: keul
Author-email: luca@keul.it
License: GPL
Keywords: plone users groups acl
Platform: UNKNOWN
Classifier: Framework :: Plone
Classifier: Framework :: Plone :: 4.0
Classifier: Framework :: Plone :: 4.1
Classifier: Framework :: Plone :: 4.2
Classifier: Framework :: Plone :: 4.3
Classifier: Framework :: Plone :: 5.0
Classifier: Programming Language :: Python
Classifier: Programming Language :: Python :: 2.7
Classifier: Development Status :: 5 - Production/Stable
